streetmanager/__init__.py
streetmanager/geojson/.gitignore
streetmanager/geojson/.swagger-codegen-ignore
streetmanager/geojson/.travis.yml
streetmanager/geojson/README.md
streetmanager/geojson/git_push.sh
streetmanager/geojson/requirements.txt
streetmanager/geojson/setup.py
streetmanager/geojson/test-requirements.txt
streetmanager/geojson/tox.ini
streetmanager/geojson/.swagger-codegen/VERSION
streetmanager/geojson/docs/ActivityActivityTypeResponse.md
streetmanager/geojson/docs/ActivityFeature.md
streetmanager/geojson/docs/ActivityProperties.md
streetmanager/geojson/docs/ActivityResponse.md
streetmanager/geojson/docs/AllOfWorkPropertiesIndustrySector.md
streetmanager/geojson/docs/AncillaryInfoFeature.md
streetmanager/geojson/docs/AncillaryInfoProperties.md
streetmanager/geojson/docs/AncillaryInfoResponse.md
streetmanager/geojson/docs/AncillaryInfoStatusResponse.md
streetmanager/geojson/docs/AncillaryInfoTypeResponse.md
streetmanager/geojson/docs/DefaultApi.md
streetmanager/geojson/docs/FeatureCollectionType.md
streetmanager/geojson/docs/FeatureType.md
streetmanager/geojson/docs/ForwardPlanFeature.md
streetmanager/geojson/docs/ForwardPlanProperties.md
streetmanager/geojson/docs/ForwardPlanResponse.md
streetmanager/geojson/docs/ForwardPlanStatusResponse.md
streetmanager/geojson/docs/GeoJSONCentrePoint.md
streetmanager/geojson/docs/GeoJSONCentrePointType.md
streetmanager/geojson/docs/GeoJSONFeatureTypeResponse.md
streetmanager/geojson/docs/GeoJSONGeometry.md
streetmanager/geojson/docs/Hs2ActLimitPhase.md
streetmanager/geojson/docs/Hs2ActLimitsFeature.md
streetmanager/geojson/docs/Hs2ActLimitsResponse.md
streetmanager/geojson/docs/IndustrySectorResponse.md
streetmanager/geojson/docs/LocationTypeResponse.md
streetmanager/geojson/docs/MaterialClassificationClassification.md
streetmanager/geojson/docs/MaterialClassificationClassificationResponse.md
streetmanager/geojson/docs/MaterialClassificationFeature.md
streetmanager-0.1.6.dist-info/METADATA
streetmanager-0.1.6.dist-info/WHEEL
streetmanager-0.1.6.dist-info/licenses/LICENSE
streetmanager-0.1.6.dist-info/RECORD
