Metadata-Version: 2.4
Name: streetmanager
Version: 0.1.6
Summary: A Python client library for the Street Manager API
Author-email: Cogna Co <info@cogna.co>
License-File: LICENSE
Requires-Python: >=3.12
Requires-Dist: certifi>=2019.9.11
Requires-Dist: python-dateutil>=2.8.2
Requires-Dist: requests>=2.25.1
Requires-Dist: six>=1.10
Requires-Dist: urllib3>=1.25.3
